typemedaddy/typemedaddy.py
typemedaddy-0.8.dist-info/METADATA
typemedaddy-0.8.dist-info/WHEEL
typemedaddy-0.8.dist-info/top_level.txt
typemedaddy-0.8.dist-info/RECORD
