Metadata-Version: 2.1
Name: typemedaddy
Version: 0.8
Summary: Derives type hints from data captured during runtime. Updates source files with type hints. USE SOURCE CONTROL before upating in-place!!!!
Author: Witold Zolnowski
Requires-Dist: autopep8>=2.0.0
